neulabs_cdk_constructs/__init__.py
neulabs_cdk_constructs/py.typed
neulabs_cdk_constructs/_jsii/__init__.py
neulabs_cdk_constructs/_jsii/neulabs-cdk-constructs@0.7.0.jsii.tgz
neulabs_cdk_constructs/aws_lambda/__init__.py
neulabs_cdk_constructs/newrelic/__init__.py
neulabs_cdk_constructs/oidc/__init__.py
neulabs_cdk_constructs/stack/__init__.py
neulabs_cdk_constructs/utils/__init__.py
neulabs_cdk_constructs-0.7.0.dist-info/LICENSE
neulabs_cdk_constructs-0.7.0.dist-info/METADATA
neulabs_cdk_constructs-0.7.0.dist-info/WHEEL
neulabs_cdk_constructs-0.7.0.dist-info/top_level.txt
neulabs_cdk_constructs-0.7.0.dist-info/RECORD
